StringFix/__init__.py
StringFix/core.py
StringFix/pybam.py
StringFix/run_sfix.py
stringfix/__init__.py
stringfix/core.py
stringfix/pybam.py
stringfix/run_sfix.py
stringfix/stringfix.py
stringfix/stringfix_blast.py
stringfix/stringfix_check_len.py
stringfix/stringfix_core.py
stringfix/stringfix_core_function_list.py
stringfix/stringfix_core_functions_useful.py
stringfix/stringfix_detect_snv.py
stringfix/stringfix_extract_tr_info.py
stringfix/stringfix_genprot.py
stringfix/stringfix_gffread.py
stringfix/stringfix_read_split_n_downsample.py
stringfix-0.8.2.dist-info/licenses/LICENSE
stringfix-0.8.2.dist-info/METADATA
stringfix-0.8.2.dist-info/WHEEL
stringfix-0.8.2.dist-info/entry_points.txt
stringfix-0.8.2.dist-info/top_level.txt
stringfix-0.8.2.dist-info/RECORD
